[
    {
        "week": 1,
        "schedule": 
            [
                {    
                    "day": 1,
                    "type": "rest",
                    "warm": false,
                    "excise" : [],
                    "cold": false,
                    "desc": "Rest"
                },
                {    
                    "day": 2,
                    "type": "rest",
                    "warm": false,
                    "excise" : [],
                    "cold": false,
                    "desc": "Rest"
                },
                {    
                    "day": 3,
                    "type": "rest",
                    "warm": false,
                    "excise" : [],
                    "cold": false,
                    "desc": "Rest"
                },
                {    
                    "day": 4,
                    "type": "easy",
                    "warm": false,
                    "excise" : [
                        {
                            "distance":10,
                            "paceType":"easy"
                        }
                    ],
                    "cold": false,
                    "desc": "Easy"
                },
                {    
                    "day": 5,
                    "type": "easy",
                    "warm": false,
                    "excise" : [
                        {
                            "distance":10,
                            "paceType":"easy"
                        }
                    ],
                    "cold": false,
                    "desc": "Easy"
                },
                {    
                    "day": 6,
                    "type": "easy",
                    "warm": false,
                    "excise" : [
                        {
                            "distance":10,
                            "paceType":"easy"
                        }
                    ],
                    "cold": false,
                    "desc": "Easy"
                },
                {    
                    "day": 7,
                    "type": "easy",
                    "warm": false,
                    "excise" : [
                        {
                            "distance":13,
                            "paceType":"easy"
                        }
                    ],
                    "cold": false,
                    "desc": "Easy"
                }
            ]
    },
    {
        "week": 2,
        "schedule": 
            [
                {    
                    "day": 1,
                    "type": "easy",
                    "warm": false,
                    "excise" : [
                        {
                            "distance":10,
                            "paceType":"easy"
                        }
                    ],
                    "cold": false,
                    "desc": "Easy"
                },
                {
                    "day": 2,
                    "type": "speed",
                    "warm": true,
                    "excise" : [
                        {
                            "distance":0.4,
                            "paceType":"speed"
                        },
                        {
                            "distance":0.4,
                            "paceType":"recover"
                        },
                        {
                            "distance":0.4,
                            "paceType":"speed"
                        },
                        {
                            "distance":0.4,
                            "paceType":"recover"
                        },
                        {
                            "distance":0.4,
                            "paceType":"speed"
                        },
                        {
                            "distance":0.4,
                            "paceType":"recover"
                        },
                        {
                            "distance":0.4,
                            "paceType":"speed"
                        },
                        {
                            "distance":0.4,
                            "paceType":"recover"
                        },
                        {
                            "distance":0.4,
                            "paceType":"speed"
                        },
                        {
                            "distance":0.4,
                            "paceType":"recover"
                        },
                        {
                            "distance":0.4,
                            "paceType":"speed"
                        },
                        {
                            "distance":0.4,
                            "paceType":"recover"
                        },
                        {
                            "distance":0.4,
                            "paceType":"speed"
                        },
                        {
                            "distance":0.4,
                            "paceType":"recover"
                        },
                        {
                            "distance":0.4,
                            "paceType":"speed"
                        },
                        {
                            "distance":0.4,
                            "paceType":"recover"
                        },
                        {
                            "distance":0.4,
                            "paceType":"speed"
                        },
                        {
                            "distance":0.4,
                            "paceType":"recover"
                        },
                        {
                            "distance":0.4,
                            "paceType":"speed"
                        },
                        {
                            "distance":0.4,
                            "paceType":"recover"
                        },
                        {
                            "distance":0.4,
                            "paceType":"speed"
                        },
                        {
                            "distance":0.4,
                            "paceType":"recover"
                        },
                        {
                            "distance":0.4,
                            "paceType":"speed"
                        }
                    ],
                    "cold": true,
                    "desc": "",
                    "excisedesc": "12x400m @5k-10k Pace,w.400m rest"
                },
                {    
                    "day": 3,
                    "type": "rest",
                    "warm": false,
                    "excise" : [],
                    "cold": false,
                    "desc": "Rest"
                },
                {    
                    "day": 4,
                    "type": "easy",
                    "warm": false,
                    "excise" : [
                        {
                            "distance":10,
                            "paceType":"easy"
                        }
                    ],
                    "cold": false,
                    "desc": "Easy"
                },
                {    
                    "day": 5,
                    "type": "easy",
                    "warm": false,
                    "excise" : [
                        {
                            "distance":10,
                            "paceType":"easy"
                        }
                    ],
                    "cold": false,
                    "desc": "Easy"
                },
                {    
                    "day": 6,
                    "type": "easy",
                    "warm": false,
                    "excise" : [
                        {
                            "distance":10,
                            "paceType":"easy"
                        }
                    ],
                    "cold": false,
                    "desc": "Easy"
                },
                {    
                    "day": 7,
                    "type": "easy",
                    "warm": false,
                    "excise" : [
                        {
                            "distance":13,
                            "paceType":"easy"
                        }
                    ],
                    "cold": false,
                    "desc": "Easy"
                }
            ]
    },
    {
        "week": 3,
        "schedule": 
            [
                {    
                    "day": 1,
                    "type": "easy",
                    "warm": false,
                    "excise" : [
                        {
                            "distance":10,
                            "paceType":"easy"
                        }
                    ],
                    "cold": false,
                    "desc": "Easy"
                },
                {    
                    "day": 2,
                    "type": "speed",
                    "warm": true,
                    "excise" : [
                        {
                            "distance":0.6,
                            "paceType":"speed"
                        },
                        {
                            "distance":0.4,
                            "paceType":"recover"
                        },
                        {
                            "distance":0.6,
                            "paceType":"speed"
                        },
                        {
                            "distance":0.4,
                            "paceType":"recover"
                        },
                        {
                            "distance":0.6,
                            "paceType":"speed"
                        },
                        {
                            "distance":0.4,
                            "paceType":"recover"
                        },
                        {
                            "distance":0.6,
                            "paceType":"speed"
                        },
                        {
                            "distance":0.4,
                            "paceType":"recover"
                        },
                        {
                            "distance":0.6,
                            "paceType":"speed"
                        },
                        {
                            "distance":0.4,
                            "paceType":"recover"
                        },
                        {
                            "distance":0.6,
                            "paceType":"speed"
                        },
                        {
                            "distance":0.4,
                            "paceType":"recover"
                        },
                        {
                            "distance":0.6,
                            "paceType":"speed"
                        },
                        {
                            "distance":0.4,
                            "paceType":"recover"
                        },
                        {
                            "distance":0.6,
                            "paceType":"speed"
                        }
                    ],
                    "cold": true,
                    "desc": "",
                    "excisedesc": "8x600m @5k-10k Pace, w. 400m rest"
                },
                {    
                    "day": 3,
                    "type": "rest",
                    "warm": false,
                    "excise" : [],
                    "cold": false,
                    "desc": "Rest"
                },
                {    
                    "day": 4,
                    "type": "tempo",
                    "warm": true,
                    "excise" : [
                        {
                            "distance":10,
                            "paceType":"tempo"
                        }
                    ],
                    "cold": true,
                    "desc": "Tempo @MP"
                },
                {    
                    "day": 5,
                    "type": "easy",
                    "warm": false,
                    "excise" : [
                        {
                            "distance":11,
                            "paceType":"easy"
                        }
                    ],
                    "cold": false,
                    "desc": "Easy"
                },
                {    
                    "day": 6,
                    "type": "easy",
                    "warm": false,
                    "excise" : [
                        {
                            "distance":10,
                            "paceType":"easy"
                        }
                    ],
                    "cold": false,
                    "desc": "Easy"
                },
                {    
                    "day": 7,
                    "type": "lsd",
                    "warm": false,
                    "excise" : [
                        {
                            "distance":16,
                            "paceType":"lsd"
                        }
                    ],
                    "cold": false,
                    "desc": "LSD"
                }
            ]
    },
    {
        "week": 4,
        "schedule": 
            [
                {    
                    "day": 1,
                    "type": "easy",
                    "warm": false,
                    "excise" : [
                        {
                            "distance":10,
                            "paceType":"easy"
                        }
                    ],
                    "cold": false,
                    "desc": "Easy"
                },
                {    
                    "day": 2,
                    "type": "speed",
                    "warm": true,
                    "excise" : [
                        {
                            "distance":0.8,
                            "paceType":"speed"
                        },
                        {
                            "distance":0.4,
                            "paceType":"recover"
                        },
                        {
                            "distance":0.8,
                            "paceType":"speed"
                        },
                        {
                            "distance":0.4,
                            "paceType":"recover"
                        },
                        {
                            "distance":0.8,
                            "paceType":"speed"
                        },
                        {
                            "distance":0.4,
                            "paceType":"recover"
                        },
                        {
                            "distance":0.8,
                            "paceType":"speed"
                        },
                        {
                            "distance":0.4,
                            "paceType":"recover"
                        },
                        {
                            "distance":0.8,
                            "paceType":"speed"
                        },
                        {
                            "distance":0.4,
                            "paceType":"recover"
                        },
                        {
                            "distance":0.8,
                            "paceType":"speed"
                        }
                    ],
                    "cold": true,
                    "desc": "",
                    "excisedesc": "6x800m @5k-10k Pace, w. 400m rest"
                },
                {    
                    "day": 3,
                    "type": "rest",
                    "warm": false,
                    "excise" : [],
                    "cold": false,
                    "desc": "Rest"
                },
                {    
                    "day": 4,
                    "type": "tempo",
                    "warm": true,
                    "excise" : [
                        {
                            "distance":8,
                            "paceType":"tempo"
                        }
                    ],
                    "cold": true,
                    "desc": "Tempo @MP"
                },
                {    
                    "day": 5,
                    "type": "easy",
                    "warm": false,
                    "excise" : [
                        {
                            "distance":10,
                            "paceType":"easy"
                        }
                    ],
                    "cold": false,
                    "desc": "Easy"
                },
                {    
                    "day": 6,
                    "type": "easy",
                    "warm": false,
                    "excise" : [
                        {
                            "distance":13,
                            "paceType":"easy"
                        }
                    ],
                    "cold": false,
                    "desc": "Easy"
                },
                {    
                    "day": 7,
                    "type": "easy",
                    "warm": false,
                    "excise" : [
                        {
                            "distance":13,
                            "paceType":"easy"
                        }
                    ],
                    "cold": false,
                    "desc": "Easy"
                }
            ]
    },
    {
        "week": 5,
        "schedule": 
            [
                {    
                    "day": 1,
                    "type": "easy",
                    "warm": false,
                    "excise" : [
                        {
                            "distance":10,
                            "paceType":"easy"
                        }
                    ],
                    "cold": false,
                    "desc": "Easy"
                },
                {    
                    "day": 2,
                    "type": "speed",
                    "warm": true,
                    "excise" : [
                        {
                            "distance":1,
                            "paceType":"speed"
                        },
                        {
                            "distance":0.4,
                            "paceType":"recover"
                        },
                        {
                            "distance":1,
                            "paceType":"speed"
                        },
                        {
                            "distance":0.4,
                            "paceType":"recover"
                        },
                        {
                            "distance":1,
                            "paceType":"speed"
                        },
                        {
                            "distance":0.4,
                            "paceType":"recover"
                        },
                        {
                            "distance":1,
                            "paceType":"speed"
                        },
                        {
                            "distance":0.4,
                            "paceType":"recover"
                        },
                        {
                            "distance":1,
                            "paceType":"speed"
                        }
                    ],
                    "cold": true,
                    "desc": "",
                    "excisedesc": "5x1 KM @5k-10k Pace, w. 400m rest"
                },
                {    
                    "day": 3,
                    "type": "rest",
                    "warm": false,
                    "excise" : [],
                    "cold": false,
                    "desc": "Rest"
                },
                {    
                    "day": 4,
                    "type": "tempo",
                    "warm": true,
                    "excise" : [
                        {
                            "distance":10,
                            "paceType":"tempo"
                        }
                    ],
                    "cold": true,
                    "desc": "Tempo @MP"
                },
                {    
                    "day": 5,
                    "type": "easy",
                    "warm": false,
                    "excise" : [
                        {
                            "distance":11,
                            "paceType":"easy"
                        }
                    ],
                    "cold": false,
                    "desc": "Easy"
                },
                {    
                    "day": 6,
                    "type": "easy",
                    "warm": false,
                    "excise" : [
                        {
                            "distance":10,
                            "paceType":"easy"
                        }
                    ],
                    "cold": false,
                    "desc": "Easy"
                },
                {    
                    "day": 7,
                    "type": "lsd",
                    "warm": false,
                    "excise" : [
                        {
                            "distance":19.5,
                            "paceType":"lsd"
                        }
                    ],
                    "cold": false,
                    "desc": "LSD"
                }
            ]
    },
    {
        "week": 6,
        "schedule": 
            [
                {    
                    "day": 1,
                    "type": "easy",
                    "warm": false,
                    "excise" : [
                        {
                            "distance":10,
                            "paceType":"easy"
                        }
                    ],
                    "cold": false,
                    "desc": "Easy"
                },
                {    
                    "day": 2,
                    "type": "speed",
                    "warm": true,
                    "excise" : [
                        {
                            "distance":1.2,
                            "paceType":"speed"
                        },
                        {
                            "distance":0.4,
                            "paceType":"recover"
                        },
                        {
                            "distance":1.2,
                            "paceType":"speed"
                        },
                        {
                            "distance":0.4,
                            "paceType":"recover"
                        },
                        {
                            "distance":1.2,
                            "paceType":"speed"
                        },
                        {
                            "distance":0.4,
                            "paceType":"recover"
                        },
                        {
                            "distance":1.2,
                            "paceType":"speed"
                        }
                    ],
                    "cold": true,
                    "desc": "",
                    "excisedesc": "4x1.2 KM @5k-10k Pace, w. 400m rest"
                },
                {    
                    "day": 3,
                    "type": "rest",
                    "warm": false,
                    "excise" : [],
                    "cold": false,
                    "desc": "Rest"
                },
                {    
                    "day": 4,
                    "type": "tempo",
                    "warm": true,
                    "excise" : [
                        {
                            "distance":11,
                            "paceType":"tempo"
                        }
                    ],
                    "cold": true,
                    "desc": "Tempo @MP"
                },
                {    
                    "day": 5,
                    "type": "easy",
                    "warm": false,
                    "excise" : [
                        {
                            "distance":10,
                            "paceType":"easy"
                        }
                    ],
                    "cold": false,
                    "desc": "Easy"
                },
                {    
                    "day": 6,
                    "type": "easy",
                    "warm": false,
                    "excise" : [
                        {
                            "distance":16,
                            "paceType":"easy"
                        }
                    ],
                    "cold": false,
                    "desc": "Easy"
                },
                {    
                    "day": 7,
                    "type": "easy",
                    "warm": false,
                    "excise" : [
                        {
                            "distance":13,
                            "paceType":"easy"
                        }
                    ],
                    "cold": false,
                    "desc": "Easy"
                }
            ]
    },
    {
        "week": 7,
        "schedule": 
            [
                {    
                    "day": 1,
                    "type": "easy",
                    "warm": false,
                    "excise" : [
                        {
                            "distance":10,
                            "paceType":"easy"
                        }
                    ],
                    "cold": false,
                    "desc": "Easy"
                },
                {    
                    "day": 2,
                    "type": "speed",
                    "warm": true,
                    "excise" : [
                        {
                            "distance":0.4,
                            "paceType":"speed"
                        },
                        {
                            "distance":0.4,
                            "paceType":"recover"
                        },
                        {
                            "distance":0.8,
                            "paceType":"speed"
                        },
                        {
                            "distance":0.4,
                            "paceType":"recover"
                        },
                        {
                            "distance":1.2,
                            "paceType":"speed"
                        },
                        {
                            "distance":0.4,
                            "paceType":"recover"
                        },
                        {
                            "distance":1.6,
                            "paceType":"speed"
                        },
                        {
                            "distance":0.4,
                            "paceType":"recover"
                        },
                        {
                            "distance":1.2,
                            "paceType":"speed"
                        },
                        {
                            "distance":0.4,
                            "paceType":"recover"
                        },
                        {
                            "distance":0.8,
                            "paceType":"speed"
                        },
                        {
                            "distance":0.4,
                            "paceType":"recover"
                        },
                        {
                            "distance":0.4,
                            "paceType":"speed"
                        }
                    ],
                    "cold": true,
                    "desc": "",
                    "excisedesc": "400m-800m-1.2 KM -1.6 KM -1.2 KM -800m-400m, w. 400m rest"
                },
                {    
                    "day": 3,
                    "type": "rest",
                    "warm": false,
                    "excise" : [],
                    "cold": false,
                    "desc": "Rest"
                },
                {    
                    "day": 4,
                    "type": "tempo",
                    "warm": true,
                    "excise" : [
                        {
                            "distance":11,
                            "paceType":"tempo"
                        }
                    ],
                    "cold": true,
                    "desc": "Tempo @MP"
                },
                {    
                    "day": 5,
                    "type": "easy",
                    "warm": false,
                    "excise" : [
                        {
                            "distance":11,
                            "paceType":"easy"
                        }
                    ],
                    "cold": false,
                    "desc": "Easy"
                },
                {    
                    "day": 6,
                    "type": "easy",
                    "warm": false,
                    "excise" : [
                        {
                            "distance":13,
                            "paceType":"easy"
                        }
                    ],
                    "cold": false,
                    "desc": "Easy"
                },
                {    
                    "day": 7,
                    "type": "lsd",
                    "warm": false,
                    "excise" : [
                        {
                            "distance":22,
                            "paceType":"lsd"
                        }
                    ],
                    "cold": false,
                    "desc": "LSD"
                }
            ]
    },
    {
        "week": 8,
        "schedule": 
            [
                {    
                    "day": 1,
                    "type": "easy",
                    "warm": false,
                    "excise" : [
                        {
                            "distance":10,
                            "paceType":"easy"
                        }
                    ],
                    "cold": false,
                    "desc": "Easy"
                },
                {    
                    "day": 2,
                    "type": "speed",
                    "warm": true,
                    "excise" : [
                        {
                            "distance":1.6,
                            "paceType":"speed"
                        },
                        {
                            "distance":0.6,
                            "paceType":"recover"
                        },
                        {
                            "distance":1.6,
                            "paceType":"speed"
                        },
                        {
                            "distance":0.6,
                            "paceType":"recover"
                        },
                        {
                            "distance":1.6,
                            "paceType":"speed"
                        }
                    ],
                    "cold": true,
                    "desc": "",
                    "excisedesc": "3x1.6 KM @5k-10k Pace， w. 600米Rest"
                },
                {    
                    "day": 3,
                    "type": "rest",
                    "warm": false,
                    "excise" : [],
                    "cold": false,
                    "desc": "Rest"
                },
                {    
                    "day": 4,
                    "type": "tempo",
                    "warm": true,
                    "excise" : [
                        {
                            "distance":11,
                            "paceType":"tempo"
                        }
                    ],
                    "cold": true,
                    "desc": "Tempo @MP"
                },
                {    
                    "day": 8,
                    "type": "easy",
                    "warm": false,
                    "excise" : [
                        {
                            "distance":10,
                            "paceType":"easy"
                        }
                    ],
                    "cold": false,
                    "desc": "Easy"
                },
                {    
                    "day": 9,
                    "type": "easy",
                    "warm": false,
                    "excise" : [
                        {
                            "distance":16,
                            "paceType":"easy"
                        }
                    ],
                    "cold": false,
                    "desc": "Easy"
                },
                {    
                    "day": 7,
                    "type": "easy",
                    "warm": false,
                    "excise" : [
                        {
                            "distance":16,
                            "paceType":"easy"
                        }
                    ],
                    "cold": false,
                    "desc": "Easy"
                }
            ]
    },
    {
        "week": 9,
        "schedule": 
            [
                {    
                    "day": 1,
                    "type": "easy",
                    "warm": false,
                    "excise" : [
                        {
                            "distance":13,
                            "paceType":"easy"
                        }
                    ],
                    "cold": false,
                    "desc": "Easy"
                },
                {    
                    "day": 2,
                    "type": "speed",
                    "warm": true,
                    "excise" : [
                        {
                            "distance":0.8,
                            "paceType":"speed"
                        },
                        {
                            "distance":0.4,
                            "paceType":"recover"
                        },
                        {
                            "distance":0.8,
                            "paceType":"speed"
                        },
                        {
                            "distance":0.4,
                            "paceType":"recover"
                        },
                        {
                            "distance":0.8,
                            "paceType":"speed"
                        },
                        {
                            "distance":0.4,
                            "paceType":"recover"
                        },
                        {
                            "distance":0.8,
                            "paceType":"speed"
                        },
                        {
                            "distance":0.4,
                            "paceType":"recover"
                        },
                        {
                            "distance":0.8,
                            "paceType":"speed"
                        },
                        {
                            "distance":0.4,
                            "paceType":"recover"
                        },
                        {
                            "distance":0.8,
                            "paceType":"speed"
                        }
                    ],
                    "cold": true,
                    "desc": "",
                    "excisedesc": "6x800m @5k-10k Pace, w. 400m rest"
                },
                {    
                    "day": 3,
                    "type": "rest",
                    "warm": false,
                    "excise" : [],
                    "cold": false,
                    "desc": "Rest"
                },
                {    
                    "day": 4,
                    "type": "tempo",
                    "warm": true,
                    "excise" : [
                        {
                            "distance":13,
                            "paceType":"tempo"
                        }
                    ],
                    "cold": true,
                    "desc": "Tempo @MP"
                },
                {    
                    "day": 5,
                    "type": "easy",
                    "warm": false,
                    "excise" : [
                        {
                            "distance":11,
                            "paceType":"easy"
                        }
                    ],
                    "cold": false,
                    "desc": "Easy"
                },
                {    
                    "day": 6,
                    "type": "easy",
                    "warm": false,
                    "excise" : [
                        {
                            "distance":13,
                            "paceType":"easy"
                        }
                    ],
                    "cold": false,
                    "desc": "Easy"
                },
                {    
                    "day": 7,
                    "type": "lsd",
                    "warm": false,
                    "excise" : [
                        {
                            "distance":24,
                            "paceType":"lsd"
                        }
                    ],
                    "cold": false,
                    "desc": "LSD"
                }
            ]
    },
    {
        "week": 10,
        "schedule": 
            [
                {    
                    "day": 1,
                    "type": "easy",
                    "warm": false,
                    "excise" : [
                        {
                            "distance":10,
                            "paceType":"easy"
                        }
                    ],
                    "cold": false,
                    "desc": "Easy"
                },
                {    
                    "day": 2,
                    "type": "speed",
                    "warm": true,
                    "excise" : [
                        {
                            "distance":1.6,
                            "paceType":"speed"
                        },
                        {
                            "distance":0.6,
                            "paceType":"recover"
                        },
                        {
                            "distance":1.6,
                            "paceType":"speed"
                        },
                        {
                            "distance":0.6,
                            "paceType":"recover"
                        },
                        {
                            "distance":1.6,
                            "paceType":"speed"
                        }
                    ],
                    "cold": true,
                    "desc": "",
                    "excisedesc": "3x1.6 KM @5k-10k Pace， w. 600米Rest"
                },
                {    
                    "day": 3,
                    "type": "rest",
                    "warm": false,
                    "excise" : [],
                    "cold": false,
                    "desc": "Rest"
                },
                {    
                    "day": 4,
                    "type": "tempo",
                    "warm": true,
                    "excise" : [
                        {
                            "distance":13,
                            "paceType":"tempo"
                        }
                    ],
                    "cold": true,
                    "desc": "Tempo @MP"
                },
                {    
                    "day": 5,
                    "type": "easy",
                    "warm": false,
                    "excise" : [
                        {
                            "distance":10,
                            "paceType":"easy"
                        }
                    ],
                    "cold": false,
                    "desc": "Easy"
                },
                {    
                    "day": 6,
                    "type": "easy",
                    "warm": false,
                    "excise" : [
                        {
                            "distance":16,
                            "paceType":"easy"
                        }
                    ],
                    "cold": false,
                    "desc": "Easy"
                },
                {    
                    "day": 7,
                    "type": "easy",
                    "warm": false,
                    "excise" : [
                        {
                            "distance":16,
                            "paceType":"easy"
                        }
                    ],
                    "cold": false,
                    "desc": "Easy"
                }
            ]
    },
    {
        "week": 11,
        "schedule": 
            [
                {    
                    "day": 8,
                    "type": "easy",
                    "warm": false,
                    "excise" : [
                        {
                            "distance":13,
                            "paceType":"easy"
                        }
                    ],
                    "cold": false,
                    "desc": "Easy"
                },
                {    
                    "day": 2,
                    "type": "strenght",
                    "warm": true,
                    "excise" : [
                        {
                            "distance":1.6,
                            "paceType":"strenght"
                        },
                        {
                            "distance":0.4,
                            "paceType":"recover"
                        },
                        {
                            "distance":1.6,
                            "paceType":"strenght"
                        },
                        {
                            "distance":0.4,
                            "paceType":"recover"
                        },
                        {
                            "distance":1.6,
                            "paceType":"strenght"
                        },
                        {
                            "distance":0.4,
                            "paceType":"recover"
                        },
                        {
                            "distance":1.6,
                            "paceType":"strenght"
                        },
                        {
                            "distance":0.4,
                            "paceType":"recover"
                        },
                        {
                            "distance":1.6,
                            "paceType":"strenght"
                        },
                        {
                            "distance":0.4,
                            "paceType":"recover"
                        },
                        {
                            "distance":1.6,
                            "paceType":"strenght"
                        }
                    ],
                    "cold": true,
                    "desc": "",
                    "excisedesc": "6x1.6 KM @MP-10s, w. 400m rest"
                },
                {    
                    "day": 3,
                    "type": "rest",
                    "warm": false,
                    "excise" : [],
                    "cold": false,
                    "desc": "Rest"
                },
                {    
                    "day": 4,
                    "type": "tempo",
                    "warm": true,
                    "excise" : [
                        {
                            "distance":13,
                            "paceType":"tempo"
                        }
                    ],
                    "cold": true,
                    "desc": "Tempo @MP"
                },
                {    
                    "day": 5,
                    "type": "easy",
                    "warm": false,
                    "excise" : [
                        {
                            "distance":11,
                            "paceType":"easy"
                        }
                    ],
                    "cold": false,
                    "desc": "Easy"
                },
                {    
                    "day": 6,
                    "type": "easy",
                    "warm": false,
                    "excise" : [
                        {
                            "distance":13,
                            "paceType":"easy"
                        }
                    ],
                    "cold": false,
                    "desc": "Easy"
                },
                {    
                    "day": 7,
                    "type": "lsd",
                    "warm": false,
                    "excise" : [
                        {
                            "distance":32,
                            "paceType":"lsd"
                        }
                    ],
                    "cold": false,
                    "desc": "LSD"
                }
            ]
    },
    {
        "week": 12,
        "schedule": 
            [
                {    
                    "day": 1,
                    "type": "easy",
                    "warm": false,
                    "excise" : [
                        {
                            "distance":10,
                            "paceType":"easy"
                        }
                    ],
                    "cold": false,
                    "desc": "Easy"
                },
                {    
                    "day": 2,
                    "type": "strenght",
                    "warm": true,
                    "excise" : [
                        {
                            "distance":2.4,
                            "paceType":"strenght"
                        },
                        {
                            "distance":0.8,
                            "paceType":"recover"
                        },
                        {
                            "distance":2.4,
                            "paceType":"strenght"
                        },
                        {
                            "distance":0.8,
                            "paceType":"recover"
                        },
                        {
                            "distance":2.4,
                            "paceType":"strenght"
                        },
                        {
                            "distance":0.8,
                            "paceType":"recover"
                        },
                        {
                            "distance":2.4,
                            "paceType":"strenght"
                        }
                    ],
                    "cold": true,
                    "desc": "",
                    "excisedesc": "4x2.4 KM @MP-10s, w. 800m rest"
                },
                {    
                    "day": 3,
                    "type": "rest",
                    "warm": false,
                    "excise" : [],
                    "cold": false,
                    "desc": "Rest"
                },
                {    
                    "day": 4,
                    "type": "tempo",
                    "warm": true,
                    "excise" : [
                        {
                            "distance":15,
                            "paceType":"tempo"
                        }
                    ],
                    "cold": true,
                    "desc": "Tempo @MP"
                },
                {    
                    "day": 5,
                    "type": "easy",
                    "warm": false,
                    "excise" : [
                        {
                            "distance":11,
                            "paceType":"easy"
                        }
                    ],
                    "cold": false,
                    "desc": "Easy"
                },
                {    
                    "day": 6,
                    "type": "easy",
                    "warm": false,
                    "excise" : [
                        {
                            "distance":13,
                            "paceType":"easy"
                        }
                    ],
                    "cold": false,
                    "desc": "Easy"
                },
                {    
                    "day": 7,
                    "type": "lsd",
                    "warm": false,
                    "excise" : [
                        {
                            "distance":16,
                            "paceType":"lsd"
                        }
                    ],
                    "cold": false,
                    "desc": "LSD"
                }
            ]
    },
    {
        "week": 13,
        "schedule": 
            [
                {    
                    "day": 1,
                    "type": "easy",
                    "warm": false,
                    "excise" : [
                        {
                            "distance":13,
                            "paceType":"easy"
                        }
                    ],
                    "cold": false,
                    "desc": "Easy"
                },
                {    
                    "day": 2,
                    "type": "strenght",
                    "warm": true,
                    "excise" : [
                        {
                            "distance":3.2,
                            "paceType":"strenght"
                        },
                        {
                            "distance":0.8,
                            "paceType":"recover"
                        },
                        {
                            "distance":3.2,
                            "paceType":"strenght"
                        },
                        {
                            "distance":0.8,
                            "paceType":"recover"
                        },
                        {
                            "distance":3.2,
                            "paceType":"strenght"
                        }
                    ],
                    "cold": true,
                    "desc": "",
                    "excisedesc": "3x3.2 KM @MP-10s, w. 800m rest"
                },
                {    
                    "day": 3,
                    "type": "rest",
                    "warm": false,
                    "excise" : [],
                    "cold": false,
                    "desc": "Rest"
                },
                {    
                    "day": 4,
                    "type": "tempo",
                    "warm": true,
                    "excise" : [
                        {
                            "distance":15,
                            "paceType":"tempo"
                        }
                    ],
                    "cold": true,
                    "desc": "Tempo @MP"
                },
                {    
                    "day": 5,
                    "type": "easy",
                    "warm": false,
                    "excise" : [
                        {
                            "distance":11,
                            "paceType":"easy"
                        }
                    ],
                    "cold": false,
                    "desc": "Easy"
                },
                {    
                    "day": 6,
                    "type": "easy",
                    "warm": false,
                    "excise" : [
                        {
                            "distance":13,
                            "paceType":"easy"
                        }
                    ],
                    "cold": false,
                    "desc": "Easy"
                },
                {    
                    "day": 7,
                    "type": "lsd",
                    "warm": false,
                    "excise" : [
                        {
                            "distance":32,
                            "paceType":"lsd"
                        }
                    ],
                    "cold": false,
                    "desc": "LSD"
                }
            ]
    },
    {
        "week": 14,
        "schedule": 
            [
                {    
                    "day": 8,
                    "type": "easy",
                    "warm": false,
                    "excise" : [
                        {
                            "distance":10,
                            "paceType":"easy"
                        }
                    ],
                    "cold": false,
                    "desc": "Easy"
                },
                {    
                    "day": 2,
                    "type": "strenght",
                    "warm": true,
                    "excise" : [
                        {
                            "distance":5,
                            "paceType":"strenght"
                        },
                        {
                            "distance":1.6,
                            "paceType":"recover"
                        },
                        {
                            "distance":5,
                            "paceType":"strenght"
                        }
                    ],
                    "cold": true,
                    "desc": "",
                    "excisedesc": "2x5 KM @MP-10s， w. 1.6 KM Rest"
                },
                {    
                    "day": 3,
                    "type": "rest",
                    "warm": false,
                    "excise" : [],
                    "cold": false,
                    "desc": "Rest"
                },
                {    
                    "day": 4,
                    "type": "tempo",
                    "warm": true,
                    "excise" : [
                        {
                            "distance":15,
                            "paceType":"tempo"
                        }
                    ],
                    "cold": true,
                    "desc": "Tempo @MP"
                },
                {    
                    "day": 5,
                    "type": "easy",
                    "warm": false,
                    "excise" : [
                        {
                            "distance":10,
                            "paceType":"easy"
                        }
                    ],
                    "cold": false,
                    "desc": "Easy"
                },
                {    
                    "day": 6,
                    "type": "easy",
                    "warm": false,
                    "excise" : [
                        {
                            "distance":16,
                            "paceType":"easy"
                        }
                    ],
                    "cold": false,
                    "desc": "Easy"
                },
                {    
                    "day": 7,
                    "type": "lsd",
                    "warm": false,
                    "excise" : [
                        {
                            "distance":16,
                            "paceType":"lsd"
                        }
                    ],
                    "cold": false,
                    "desc": "LSD"
                }
            ]
    },
    {
        "week": 15,
        "schedule": 
            [
                {    
                    "day": 1,
                    "type": "easy",
                    "warm": false,
                    "excise" : [
                        {
                            "distance":13,
                            "paceType":"easy"
                        }
                    ],
                    "cold": false,
                    "desc": "Easy"
                },
                {    
                    "day": 2,
                    "type": "strenght",
                    "warm": true,
                    "excise" : [
                        {
                            "distance":3.2,
                            "paceType":"strenght"
                        },
                        {
                            "distance":0.8,
                            "paceType":"recover"
                        },
                        {
                            "distance":3.2,
                            "paceType":"strenght"
                        },
                        {
                            "distance":0.8,
                            "paceType":"recover"
                        },
                        {
                            "distance":3.2,
                            "paceType":"strenght"
                        }
                    ],
                    "cold": true,
                    "desc": "",
                    "excisedesc": "3x3.2 KM @MP-10s, w. 800m rest"
                },
                {    
                    "day": 3,
                    "type": "rest",
                    "warm": false,
                    "excise" : [],
                    "cold": false,
                    "desc": "Rest"
                },
                {    
                    "day": 4,
                    "type": "tempo",
                    "warm": true,
                    "excise" : [
                        {
                            "distance":16,
                            "paceType":"tempo"
                        }
                    ],
                    "cold": true,
                    "desc": "Tempo @MP"
                },
                {    
                    "day": 5,
                    "type": "easy",
                    "warm": false,
                    "excise" : [
                        {
                            "distance":11,
                            "paceType":"easy"
                        }
                    ],
                    "cold": false,
                    "desc": "Easy"
                },
                {    
                    "day": 6,
                    "type": "easy",
                    "warm": false,
                    "excise" : [
                        {
                            "distance":13,
                            "paceType":"easy"
                        }
                    ],
                    "cold": false,
                    "desc": "Easy"
                },
                {    
                    "day": 7,
                    "type": "lsd",
                    "warm": false,
                    "excise" : [
                        {
                            "distance":32,
                            "paceType":"lsd"
                        }
                    ],
                    "cold": false,
                    "desc": "LSD"
                }
            ]
    },
    {
        "week": 16,
        "schedule": 
            [
                {    
                    "day": 8,
                    "type": "easy",
                    "warm": false,
                    "excise" : [
                        {
                            "distance":10,
                            "paceType":"easy"
                        }
                    ],
                    "cold": false,
                    "desc": "Easy"
                },
                {    
                    "day": 2,
                    "type": "strenght",
                    "warm": true,
                    "excise" : [
                        {
                            "distance":2.4,
                            "paceType":"strenght"
                        },
                        {
                            "distance":0.8,
                            "paceType":"recover"
                        },
                        {
                            "distance":2.4,
                            "paceType":"strenght"
                        },
                        {
                            "distance":0.8,
                            "paceType":"recover"
                        },
                        {
                            "distance":2.4,
                            "paceType":"strenght"
                        },
                        {
                            "distance":0.8,
                            "paceType":"recover"
                        },
                        {
                            "distance":2.4,
                            "paceType":"strenght"
                        }
                    ],
                    "cold": true,
                    "desc": "",
                    "excisedesc": "4x2.4 KM @MP-10s, w. 800m rest"
                },
                {    
                    "day": 3,
                    "type": "rest",
                    "warm": false,
                    "excise" : [],
                    "cold": false,
                    "desc": "Rest"
                },
                {    
                    "day": 4,
                    "type": "tempo",
                    "warm": true,
                    "excise" : [
                        {
                            "distance":16,
                            "paceType":"tempo"
                        }
                    ],
                    "cold": true,
                    "desc": "Tempo @MP"
                },
                {    
                    "day": 5,
                    "type": "easy",
                    "warm": false,
                    "excise" : [
                        {
                            "distance":10,
                            "paceType":"easy"
                        }
                    ],
                    "cold": false,
                    "desc": "Easy"
                },
                {    
                    "day": 6,
                    "type": "easy",
                    "warm": false,
                    "excise" : [
                        {
                            "distance":16,
                            "paceType":"easy"
                        }
                    ],
                    "cold": false,
                    "desc": "Easy"
                },
                {    
                    "day": 7,
                    "type": "lsd",
                    "warm": false,
                    "excise" : [
                        {
                            "distance":16,
                            "paceType":"lsd"
                        }
                    ],
                    "cold": false,
                    "desc": "LSD"
                }
            ]
    },
    {
        "week": 17,
        "schedule": 
            [
                {    
                    "day": 1,
                    "type": "easy",
                    "warm": false,
                    "excise" : [
                        {
                            "distance":13,
                            "paceType":"easy"
                        }
                    ],
                    "cold": false,
                    "desc": "Easy"
                },
                {    
                    "day": 2,
                    "type": "strenght",
                    "warm": true,
                    "excise" : [
                        {
                            "distance":1.6,
                            "paceType":"strenght"
                        },
                        {
                            "distance":0.4,
                            "paceType":"recover"
                        },
                        {
                            "distance":1.6,
                            "paceType":"strenght"
                        },
                        {
                            "distance":0.4,
                            "paceType":"recover"
                        },
                        {
                            "distance":1.6,
                            "paceType":"strenght"
                        },
                        {
                            "distance":0.4,
                            "paceType":"recover"
                        },
                        {
                            "distance":1.6,
                            "paceType":"strenght"
                        },
                        {
                            "distance":0.4,
                            "paceType":"recover"
                        },
                        {
                            "distance":1.6,
                            "paceType":"strenght"
                        },
                        {
                            "distance":0.4,
                            "paceType":"recover"
                        },
                        {
                            "distance":1.6,
                            "paceType":"strenght"
                        }
                    ],
                    "cold": true,
                    "desc": "",
                    "excisedesc": "6x1.6 KM @MP-10s, w. 400m rest"
                },
                {    
                    "day": 3,
                    "type": "rest",
                    "warm": false,
                    "excise" : [],
                    "cold": false,
                    "desc": "Rest"
                },
                {    
                    "day": 4,
                    "type": "tempo",
                    "warm": true,
                    "excise" : [
                        {
                            "distance":16,
                            "paceType":"tempo"
                        }
                    ],
                    "cold": true,
                    "desc": "Tempo @MP"
                },
                {    
                    "day": 5,
                    "type": "easy",
                    "warm": false,
                    "excise" : [
                        {
                            "distance":11,
                            "paceType":"easy"
                        }
                    ],
                    "cold": false,
                    "desc": "Easy"
                },
                {    
                    "day": 6,
                    "type": "easy",
                    "warm": false,
                    "excise" : [
                        {
                            "distance":13,
                            "paceType":"easy"
                        }
                    ],
                    "cold": false,
                    "desc": "Easy"
                },
                {    
                    "day": 7,
                    "type": "lsd",
                    "warm": false,
                    "excise" : [
                        {
                            "distance":13,
                            "paceType":"lsd"
                        }
                    ],
                    "cold": false,
                    "desc": "LSD"
                }
            ]
    },
    {
        "week": 18,
        "schedule": 
            [
                {    
                    "day": 1,
                    "type": "easy",
                    "warm": false,
                    "excise" : [
                        {
                            "distance":10,
                            "paceType":"easy"
                        }
                    ],
                    "cold": false,
                    "desc": "Easy"
                },
                {    
                    "day": 2,
                    "type": "easy",
                    "warm": false,
                    "excise" : [
                        {
                            "distance":8,
                            "paceType":"easy"
                        }
                    ],
                    "cold": false,
                    "desc": "Easy"
                },
                {    
                    "day": 3,
                    "type": "rest",
                    "warm": false,
                    "excise" : [],
                    "cold": false,
                    "desc": "Rest"
                },
                {    
                    "day": 4,
                    "type": "easy",
                    "warm": false,
                    "excise" : [
                        {
                            "distance":10,
                            "paceType":"easy"
                        }
                    ],
                    "cold": false,
                    "desc": "Easy"
                },
                {    
                    "day": 5,
                    "type": "easy",
                    "warm": false,
                    "excise" : [
                        {
                            "distance":10,
                            "paceType":"easy"
                        }
                    ],
                    "cold": false,
                    "desc": "Easy"
                },
                {    
                    "day": 6,
                    "type": "easy",
                    "warm": false,
                    "excise" : [
                        {
                            "distance":5,
                            "paceType":"easy"
                        }
                    ],
                    "cold": false,
                    "desc": "Easy"
                },
                {    
                    "day": 7,
                    "type": "D-day",
                    "warm": false,
                    "excise" : [
                    ],
                    "cold": false,
                    "desc": "比赛日!"
                }
            ]
    }
]